{
    "countQuestion": 40,
    "defaultNumbersOfCorrectReplies": 1,
    "indentBetweenQuestions": 1,
    "numbersOfReplies": 1,
    "questions": [
    	{
            "height": "125",
            "number": 1,
            "width": "100",
            "x": "450",
            "y": "170"
        },
        {
            "height": "125",
            "number": 2,
            "width": "100",
            "x": "450",
            "y": "305"
        },
        {
            "height": "125",
            "number": 3,
            "width": "100",
            "x": "450",
            "y": "440"
        },
        {
            "height": "125",
            "number": 4,
            "width": "100",
            "x": "450",
            "y": "575"
        },
        {
            "height": "125",
            "number": 5,
            "width": "100",
            "x": "450",
            "y": "710"
        },
        {
            "height": "125",
            "number": 6,
            "width": "100",
            "x": "450",
            "y": "845"
        },
        {
            "height": "125",
            "number": 7,
            "width": "100",
            "x": "450",
            "y": "980"
        },
        {
            "height": "125",
            "number": 8,
            "width": "100",
            "x": "450",
            "y": "1115"
        },
        {
            "height": "125",
            "number": 9,
            "width": "100",
            "x": "700",
            "y": "170"
        },
        {
            "height": "125",
            "number": 10,
            "width": "100",
            "x": "700",
            "y": "305"
        },
        {
            "height": "125",
            "number": 11,
            "width": "100",
            "x": "700",
            "y": "435"
        },
        {
            "height": "125",
            "number": 12,
            "width": "100",
            "x": "700",
            "y": "575"
        },
        {
            "height": "125",
            "number": 13,
            "width": "100",
            "x": "700",
            "y": "710"
        },
        {
            "height": "125",
            "number": 14,
            "width": "100",
            "x": "700",
            "y": "845"
        },
        {
            "height": "125",
            "number": 15,
            "width": "100",
            "x": "700",
            "y": "980"
        },
        {
            "height": "125",
            "number": 16,
            "width": "100",
            "x": "700",
            "y": "1115"
        },
        {
            "height": "125",
            "number": 17,
            "width": "100",
            "x": "960",
            "y": "170"
        },
        {
            "height": "125",
            "number": 18,
            "width": "100",
            "x": "960",
            "y": "305"
        },
        {
            "height": "125",
            "number": 19,
            "width": "100",
            "x": "960",
            "y": "440"
        },
        {
            "height": "125",
            "number": 20,
            "width": "100",
            "x": "960",
            "y": "575"
        },
        {
            "height": "125",
            "number": 21,
            "width": "100",
            "x": "960",
            "y": "710"
        },
        {
            "height": "125",
            "number": 22,
            "width": "100",
            "x": "960",
            "y": "845"
        },
        {
            "height": "125",
            "number": 23,
            "width": "100",
            "x": "960",
            "y": "980"
        },
        {
            "height": "125",
            "number": 24,
            "width": "100",
            "x": "960",
            "y": "1115"
        },
        {
            "height": "125",
            "number": 25,
            "width": "100",
            "x": "1220",
            "y": "170"
        },
        {
            "height": "125",
            "number": 26,
            "width": "100",
            "x": "1220",
            "y": "305"
        },
        {
            "height": "125",
            "number": 27,
            "width": "100",
            "x": "1220",
            "y": "440"
        },
        {
            "height": "125",
            "number": 28,
            "width": "100",
            "x": "1220",
            "y": "575"
        },
        {
            "height": "125",
            "number": 29,
            "width": "100",
            "x": "1220",
            "y": "710"
        },
        {
            "height": "125",
            "number": 30,
            "width": "100",
            "x": "1220",
            "y": "845"
        },
        {
            "height": "125",
            "number": 31,
            "width": "100",
            "x": "1220",
            "y": "980"
        },
        {
            "height": "125",
            "number": 32,
            "width": "100",
            "x": "1220",
            "y": "1115"
        },
        {
            "height": "125",
            "number": 33,
            "width": "100",
            "x": "1480",
            "y": "170"
        },
        {
            "height": "125",
            "number": 34,
            "width": "100",
            "x": "1480",
            "y": "305"
        },
        {
            "height": "125",
            "number": 35,
            "width": "100",
            "x": "1480",
            "y": "440"
        },
        {
            "height": "125",
            "number": 36,
            "width": "100",
            "x": "1480",
            "y": "575"
        },
        {
            "height": "125",
            "number": 37,
            "width": "100",
            "x": "1480",
            "y": "710"
        },
        {
            "height": "125",
            "number": 38,
            "width": "100",
            "x": "1480",
            "y": "845"
        },
        {
            "height": "125",
            "number": 39,
            "width": "100",
            "x": "1480",
            "y": "980"
        },
        {
            "height": "125",
            "number": 40,
            "width": "100",
            "x": "1480",
            "y": "1115"
        }
    ]
}
